Metadata-Version: 2.1
Name: pysnag
Version: 0.0.3
Summary: lib for easy access to bugsnags's APIv2
Home-page: https://github.com/jjabba/pysnag
Author: Karl Berggren
Author-email: kalle@jjabba.com
License: UNKNOWN
Platform: UNKNOWN
Classifier: Programming Language :: Python :: 3
Classifier: License :: OSI Approved :: MIT License
Classifier: Operating System :: OS Independent
Requires-Python: >=3.6
